{
  "generatedAt": "2026-05-26T05:19:43.388795+00:00",
  "slug": "bank-guarantee-issuance-dogfood-2026-05-26",
  "file": "bank-guarantee-issuance-v1.md",
  "created": [
    "CP-BGID-001",
    "CP-BGID-002",
    "CP-BGID-003",
    "EX-BGID-001",
    "EX-BGID-002",
    "M-BGID-001",
    "PP-BGID-001",
    "PP-BGID-002",
    "PS-BGID-001",
    "PS-BGID-002",
    "PS-BGID-003",
    "PS-BGID-004",
    "PS-BGID-005",
    "PS-BGID-006",
    "REG-BGID-001",
    "REG-BGID-002",
    "ROLE-BGID-001",
    "ROLE-BGID-002",
    "ROLE-BGID-003",
    "ROLE-BGID-004",
    "ROLE-BGID-005",
    "ROLE-BGID-006",
    "SYS-BGID-001",
    "SYS-BGID-002",
    "SYS-BGID-003",
    "SYS-BGID-004"
  ],
  "updated": [],
  "conflicts": [],
  "corrections": []
}
