{
  "slug": "bank-guarantee-issuance",
  "queue": [
    "BGI",
    "PS-BGI-001",
    "PS-BGI-002",
    "PS-BGI-003",
    "PS-BGI-004",
    "PS-BGI-005",
    "PS-BGI-006",
    "ROLE-BGI-001",
    "ROLE-BGI-003",
    "ROLE-BGI-002",
    "ROLE-BGI-004",
    "ROLE-BGI-005",
    "ROLE-BGI-006",
    "EX-BGI-002",
    "EX-BGI-001",
    "EX-BGI-003",
    "CP-BGI-003",
    "CP-BGI-001",
    "CP-BGI-002",
    "REG-BGI-001",
    "REG-BGI-002",
    "PP-BGI-001",
    "PP-BGI-002",
    "SYS-BGI-001",
    "SYS-BGI-002",
    "SYS-BGI-003",
    "SYS-BGI-004",
    "M-BGI-001"
  ],
  "cursor": 28,
  "total": 28,
  "done": true,
  "startedAt": "2026-05-19T20:35:26.509551+00:00",
  "updatedAt": "2026-05-19T21:45:57.635803+00:00"
}
